{
	"connection_key": "request",
	"result": true,
	"redis_key": "abcdefg",
	"filepath": "/var/lib/aion/Data/rededge_sdc/abcdef.json",
	"api_status_code": 200,
	"runtime_session_id": "boi9ar543dg91ipdnspi099u231280ab0v8af0ew",
	"business_partner": null,
	"service_label": "DELIVERY_DOCUMENT",
	"api_type": "",
	"DeliveryDocument": {
		"DeliveryDocument": null,
		"Buyer": 101,
		"Seller": 201,
		"ReferenceDocument": 116,
		"ReferenceDocumentItem": null,
		"OrderID": null,
		"OrderItem": null,
		"ContractType": "",
		"OrderVaridityStartDate": "",
		"OrderValidityEndDate": "",
		"InvoiceScheduleStartDate": "2022-11-23",
		"InvoiceScheduleEndDate": "",
		"IssuingPlantTimeZone": "",
		"ReceivingPlantTimeZone": "",
		"DocumentDate": "2022-11-25",
		"PlannedGoodsIssueDate": "",
		"PlannedGoodsIssueTime": "",
		"PlannedGoodsReceiptDate": "",
		"PlannedGoodsReceiptTime": "",
		"BillingDocumentDate": "",
		"CompleteDeliveryIsDefined": null,
		"OverallDeliveryStatus": "",
		"CreationDate": "",
		"CreationTime": "",
		"IssuingBlockReason": null,
		"ReceivingBlockReason": null,
		"GoodsIssueOrReceiptSlipNumber": "",
		"HeaderBillingStatus": "",
		"HeaderBillingConfStatus": "",
		"HeaderBillingBlockReason": null,
		"HeaderGrossWeight": null,
		"HeaderNetWeight": null,
		"HeaderVolumeUnit": "",
		"HeaderWeightUnit": "",
		"Incoterms": "",
		"IsExportImportDelivery": null,
		"LastChangeDate": "",
		"IssuingPlantBusinessPartner": "",
		"IssuingPlant": "",
		"ReceivingPlant": "",
		"ReceivingPlantBusinessPartner": "",
		"DeliverToParty": null,
		"DeliverFromParty": null,
		"TransactionCurrency": "",
		"OverallDelivReltdBillgStatus": "",
		"HeaderPartner": [
			{
				"PartnerFunction": "",
				"BusinessPartner": null,
				"BusinessPartnerFullName": "",
				"BusinessPartnerName": "",
				"Organization": "",
				"Country": "",
				"Language": "",
				"Currency": "",
				"ExternalDocumentID": "",
				"AddressID": null,
				"HeaderPartnerContact": [
					{
						"PartnerFunction": "",
						"ContactID": null,
						"BusinessPartner": "",
						"ContactPersonName": "",
						"EmailAddress": "",
						"PhoneNumber": "",
						"MobilePhoneNumber": "",
						"FaxNumber": "",
						"ContactTag1": "",
						"ContactTag2": "",
						"ContactTag3": "",
						"ContactTag4": ""
					}
				],
				"HeaderPartnerPlant": [
					{
						"Plant": ""
					}
				]
			}
		],
		"HeaderPDF": [
			{
				"DocType": "",
				"DocVersionID": null,
				"DocID": "",
				"DocIssuerBusinessPartner": null,
				"FileName": ""
			}
		],
		"Address": [
			{
				"AddressID": null,
				"PostalCode": "",
				"LocalRegion": "",
				"Country": "",
				"District": "",
				"StreetName": "",
				"CityName": "",
				"Building": "",
				"Floor": null,
				"Room": null
			}
		],
		"DeliveryDocumentItem": [
			{
				"DeliveryDocumentItem": null,
				"DeliveryDocumentItemCategory": "",
				"DeliveryDocumentItemText": "",
				"Product": "",
				"ProductStandardID": "",
				"ProductGroup": "",
				"BaseUnit": "",
				"OriginalDeliveryQuantity": null,
				"DeliveryQuantityUnit": "",
				"ActualGoodsIssueDate": "",
				"ActualGoodsIssueTime": "",
				"ActualGoodsReceiptDate": "",
				"ActualGoodsReceiptTime": "",
				"ActualGoodsIssueQtyInBaseUnit": null,
				"ActualGoodsIssueQuantity": null,
				"ActualGoodsReceiptQtyInBaseUnit": null,
				"ActualGoodsReceiptQuantity": null,
				"CompleteItemDeliveryIsDefined": null,
				"StockConfirmationPartnerFunction": "",
				"StockConfirmationBusinessPartner": null,
				"StockConfirmationPlant": "",
				"StockConfirmationPolicy": "",
				"StockConfirmationStatus": "",
				"ProductionPlantPartnerFunction": "",
				"ProductionPlantBusinessPartner": "",
				"ProductionPlant": "",
				"ProductionPlantStorageLocation": "",
				"IssuingPlantPartnerFunction": "",
				"IssuingPlantBusinessPartner": "",
				"IssuingPlant": "",
				"IssuingPlantStorageLocation": "",
				"ReceivingPlantPartnerFunction": "",
				"ReceivingPlantBusinessPartner": "",
				"ReceivingPlant": "",
				"ReceivingPlantStorageLocation": "",
				"ProductIsBatchManagedInProductionPlant": null,
				"ProductIsBatchManagedInIssuingPlant": null,
				"ProductIsBatchManagedInReceivingPlant": null,
				"BatchMgmtPolicyInProductionPlant": "",
				"BatchMgmtPolicyInIssuingPlant": "",
				"BatchMgmtPolicyInReceivingPlant": "",
				"ProductionPlantBatch": "",
				"IssuingPlantBatch": "",
				"ReceivingPlantBatch": "",
				"ProductionPlantBatchValidityStartDate": "",
				"ProductionPlantBatchValidityEndDate": "",
				"IssuingPlantBatchValidityStartDate": "",
				"IssuingPlantBatchValidityEndDate": "",
				"ReceivingPlantBatchValidityStartDate": "",
				"ReceivingPlantBatchValidityEndDate": "",
				"CreationDate": "",
				"CreationTime": "",
				"ItemBillingStatus": "",
				"ItemBillingConfStatus": "",
				"SalesCostGLAccount": "",
				"ReceivingGLAccount": "",
				"IssuingGoodsMovementType": "",
				"ReceivingGoodsMovementType": "",
				"ItemBillingBlockReason": null,
				"ItemCompleteDeliveryIsDefined": null,
				"ItemDeliveryIncompletionStatus": "",
				"ItemGrossWeight": null,
				"ItemNetWeight": null,
				"ItemWeightUnit": "",
				"ItemIsBillingRelevant": null,
				"LastChangeDate": "",
				"OrderID": null,
				"OrderItem": null,
				"OrderType": "",
				"ContractType": "",
				"OrderVaridityStartDate": "",
				"OrderValidityEndDate": "",
				"InvoiceScheduleStartDate": "",
				"InvoiceScheduleEndDate": "",
				"ProductAvailabilityDate": "",
				"Project": "",
				"ReferenceDocument": null,
				"ReferenceDocumentItem": null,
				"TaxClassification": "",
				"ProductTaxClassification": "",
				"BPAccountAssignmentGroup": "",
				"ProductAccountAssignmentGroup": "",
				"TaxCode": "",
				"TaxRate": null,
				"CountryOfOrigin": "",
				"ItemPartner": [
					{
						"PartnerFunction": "",
						"BusinessPartner": null,
						"ItemPartnerPlant": [
							{
								"Plant": ""
							}
						]
					}
				]
			}
		]
	},
	"api_schema": "DPFMDeliveryDocumentReads",
	"accepter": [
		"Header",
		"HeaderPartner"
	],
	"delivery_document_id": null,
	"deleted": false
}